easy_thumbnails_rest/__init__.py
easy_thumbnails_rest/serializers.py
easy_thumbnails_rest-1.1.4.dist-info/LICENSE
easy_thumbnails_rest-1.1.4.dist-info/METADATA
easy_thumbnails_rest-1.1.4.dist-info/WHEEL
easy_thumbnails_rest-1.1.4.dist-info/top_level.txt
easy_thumbnails_rest-1.1.4.dist-info/RECORD
