Metadata-Version: 2.1
Name: easy-thumbnails-rest
Version: 1.1.4
Summary: Easy Thumbnails Fields for Django Rest API
Home-page: https://github.com/modbender/easy-thumbnails-rest
Author: Yashas H R
Author-email: rameshmamathayashas@gmail.com
License: UNKNOWN
Platform: any
Classifier: Environment :: Web Environment
Classifier: Framework :: Django
Classifier: Intended Audience :: Developers
Classifier: Operating System :: OS Independent
Classifier: Programming Language :: Python
Classifier: Programming Language :: Python :: 3
Classifier: Programming Language :: Python :: 3 :: Only
Classifier: Topic :: Software Development :: Libraries :: Python Modules
Requires-Python: >=3.5
License-File: LICENSE
